{
  "generatedAt": "2026-03-22T18:04:03.962Z",
  "source": "sanity",
  "enabled": true,
  "siteUrl": "https://www.askqualy.com",
  "index": {
    "tr": {
      "path": "/blog",
      "title": "Blog | Qualy",
      "description": "Qualy hakkinda guncellemeler, kullanici hikayeleri ve urun notlari.",
      "robots": "noindex,follow"
    },
    "en": {
      "path": "/en/blog",
      "title": "Blog | Qualy",
      "description": "Updates, product notes, and customer stories from Qualy.",
      "robots": "noindex,follow"
    }
  },
  "posts": [],
  "groups": []
}
